demo/biencoder_sweep.py
demo/biencoder_sweep_rrf.py
demo/bm25_sweep.py
suiteeval/__init__.py
suiteeval/_optional.py
suiteeval/context.py
suiteeval/utility.py
suiteeval/pt_docs/api.rst
suiteeval/pt_docs/conf.py
suiteeval/pt_docs/index.rst
suiteeval/pt_docs/suites.rst
suiteeval/suite/__init__.py
suiteeval/suite/base.py
suiteeval/suite/beir.py
suiteeval/suite/bright.py
suiteeval/suite/lotte.py
suiteeval/suite/msmarco.py
suiteeval/suite/nanobeir.py
suiteeval-0.1.5.dist-info/licenses/LICENSE
suiteeval-0.1.5.dist-info/METADATA
suiteeval-0.1.5.dist-info/WHEEL
suiteeval-0.1.5.dist-info/top_level.txt
suiteeval-0.1.5.dist-info/RECORD
