Metadata-Version: 2.4
Name: suiteeval
Version: 0.1.5
Summary: Tools for running IR Evaluation Suites
Author-email: Sean MacAvaney <sean.macavaney@glasgow.ac.uk>, Andrew Parry <0andrewparry@gmail.com>
Project-URL: Repository, https://github.com/mrparryparry/suiteeval
Project-URL: Bug Tracker, https://github.com/mrparryparry/suiteeval/issues
Classifier: Programming Language :: Python
Classifier: Operating System :: OS Independent
Classifier: Topic :: Text Processing
Classifier: Topic :: Text Processing :: Indexing
Requires-Python: >=3.10
License-File: LICENSE
Requires-Dist: pyterrier
Dynamic: license-file
